netissuestools/Superfast_multithread_ping.py
netissuestools/__init__.py
netissuestools-1.0.1.dist-info/METADATA
netissuestools-1.0.1.dist-info/WHEEL
netissuestools-1.0.1.dist-info/entry_points.txt
netissuestools-1.0.1.dist-info/top_level.txt
netissuestools-1.0.1.dist-info/RECORD
