Metadata-Version: 2.1
Name: netissuestools
Version: 1.0.1
Summary: To solve some network issues
Home-page: https://github.com/Wing9897/Network_issues_solution.git
Author: wing
Author-email: tomt99688@gmail.com
Classifier: Programming Language :: Python :: 3
Classifier: License :: OSI Approved :: MIT License
Classifier: Operating System :: OS Independent
Requires-Python: >=3.6
Requires-Dist: ping3 >=4.0.0
